aisuite4cn/__init__.py
aisuite4cn/agentscope/__init__.py
aisuite4cn/agentscope/_agentscope_client.py
aisuite4cn/agentscope/_openai_compatible_formatter.py
aisuite4cn/base_provider.py
aisuite4cn/client.py
aisuite4cn/framework/__init__.py
aisuite4cn/framework/chat_completion_response.py
aisuite4cn/framework/choice.py
aisuite4cn/framework/message.py
aisuite4cn/framework/provider_interface.py
aisuite4cn/llama_index/__init__.py
aisuite4cn/llama_index/llama_index_client.py
aisuite4cn/llama_index/utils.py
aisuite4cn/provider.py
aisuite4cn/providers/__init__.py
aisuite4cn/providers/ark_provider.py
aisuite4cn/providers/custom_provider.py
aisuite4cn/providers/dashscope_provider.py
aisuite4cn/providers/deepseek_provider.py
aisuite4cn/providers/dmxapi_provider.py
aisuite4cn/providers/hunyuan_provider.py
aisuite4cn/providers/longcat_provider.py
aisuite4cn/providers/minimax_provider.py
aisuite4cn/providers/moonshot_provider.py
aisuite4cn/providers/ollama_provider.py
aisuite4cn/providers/qianfan_provider.py
aisuite4cn/providers/qwen_provider.py
aisuite4cn/providers/siliconflow_provider.py
aisuite4cn/providers/spark_provider.py
aisuite4cn/providers/yunwu_provider.py
aisuite4cn/providers/zhipuai_provider.py
aisuite4cn-1.1.5.dist-info/METADATA
aisuite4cn-1.1.5.dist-info/WHEEL
aisuite4cn-1.1.5.dist-info/licenses/LICENSE
aisuite4cn-1.1.5.dist-info/RECORD
