Metadata-Version: 2.4
Name: aisuite4cn
Version: 1.1.5
Summary: Uniform access layer for LLMs of China
License-File: LICENSE
Author: 胡伟
Author-email: 3314672@qq.com
Requires-Python: >=3.10, <4
Classifier: Programming Language :: Python :: 3
Classifier: Programming Language :: Python :: 3.10
Classifier: Programming Language :: Python :: 3.11
Classifier: Programming Language :: Python :: 3.12
Classifier: Programming Language :: Python :: 3.13
Classifier: Programming Language :: Python :: 3.14
Provides-Extra: agentscope
Provides-Extra: all
Provides-Extra: ark
Provides-Extra: deepseek
Provides-Extra: dmxapi
Provides-Extra: hunyuan
Provides-Extra: llama-index
Provides-Extra: longcat
Provides-Extra: minimax
Provides-Extra: moonshot
Provides-Extra: ollama
Provides-Extra: openai
Provides-Extra: qianfan
Provides-Extra: qwen
Provides-Extra: siliconflow
Provides-Extra: spark
Provides-Extra: zhipuai
Requires-Dist: agentscope (>=1.0.0,<2.0.0) ; extra == "agentscope"
Requires-Dist: agentscope ; extra == "all"
Requires-Dist: httpx (>=0.27.0)
Requires-Dist: llama-index ; extra == "all"
Requires-Dist: llama-index-core (>=0.13.4,<0.14.0) ; extra == "llama-index"
Requires-Dist: openai (>=1.82.1) ; extra == "openai"
Requires-Dist: openai ; extra == "all"
Requires-Dist: openai ; extra == "ark"
Requires-Dist: openai ; extra == "deepseek"
Requires-Dist: openai ; extra == "dmxapi"
Requires-Dist: openai ; extra == "hunyuan"
Requires-Dist: openai ; extra == "longcat"
Requires-Dist: openai ; extra == "minimax"
Requires-Dist: openai ; extra == "moonshot"
Requires-Dist: openai ; extra == "ollama"
Requires-Dist: openai ; extra == "qianfan"
Requires-Dist: openai ; extra == "qwen"
Requires-Dist: openai ; extra == "siliconflow"
Requires-Dist: openai ; extra == "spark"
Requires-Dist: openai ; extra == "zhipuai"
Requires-Dist: pydantic (>=2.10.3,<3.0.0)
Requires-Dist: python-box (>=7.3.2,<8.0.0)
Requires-Dist: python-dotenv (>=1.1.0,<2.0.0)
Requires-Dist: qianfan (>=0.4.12.3) ; extra == "qianfan"
Requires-Dist: qianfan ; extra == "all"
